weio/_NEWFILE_TEMPLATE - Copy.py
weio/_NEWFILE_TEMPLATE.py
weio/__init__.py
weio/airfoil_file.py
weio/amrwind_file.py
weio/bladed_out_file.py
weio/bmodes_out_file.py
weio/cactus_element_file.py
weio/cactus_file.py
weio/converters.py
weio/csv_file.py
weio/excel_file.py
weio/fast_input_deck.py
weio/fast_input_file.py
weio/fast_input_file_graph.py
weio/fast_linearization_file.py
weio/fast_output_file.py
weio/fast_summary_file.py
weio/fast_wind_file.py
weio/file.py
weio/file_formats.py
weio/flex_blade_file.py
weio/flex_doc_file.py
weio/flex_out_file.py
weio/flex_profile_file.py
weio/flex_wavekin_file.py
weio/gnuplot_file.py
weio/hawc2_ae_file.py
weio/hawc2_dat_file.py
weio/hawc2_htc_file.py
weio/hawc2_pc_file.py
weio/hawc2_st_file.py
weio/hawcstab2_cmb_file.py
weio/hawcstab2_ind_file.py
weio/hawcstab2_pwr_file.py
weio/mannbox_file.py
weio/mannbox_input_file.py
weio/matlabmat_file.py
weio/mini_yaml.py
weio/netcdf_file.py
weio/parquet_file.py
weio/pickle_file.py
weio/plot3d_file.py
weio/raawmat_file.py
weio/rosco_discon_file.py
weio/rosco_performance_file.py
weio/tdms_file.py
weio/tecplot_file.py
weio/turbsim_file.py
weio/turbsim_ts_file.py
weio/user.py
weio/vtk_file.py
weio/yaml_file.py
weio/tools/__init__.py
weio/tools/graph.py
weio/wetb/__init__.py
weio/wetb/hawc2/Hawc2io.py
weio/wetb/hawc2/__init__.py
weio/wetb/hawc2/ae_file.py
weio/wetb/hawc2/htc_contents.py
weio/wetb/hawc2/htc_extensions.py
weio/wetb/hawc2/htc_file.py
weio/wetb/hawc2/htc_file_set.py
weio/wetb/hawc2/pc_file.py
weio/wetb/hawc2/st_file.py
weio-2.0.0.dist-info/licenses/LICENSE.TXT
weio-2.0.0.dist-info/METADATA
weio-2.0.0.dist-info/WHEEL
weio-2.0.0.dist-info/top_level.txt
weio-2.0.0.dist-info/RECORD
